Metadata-Version: 1.0
Name: DiscordBar
Version: 0.0.3
Summary: Progressbar for discord, docs here https://github.com/Animatea/DiscordProgressbar
Home-page: UNKNOWN
Author: UNKNOWN
Author-email: den25340@gmail.com
License: UNKNOWN
Platform: UNKNOWN
